hackwithharsha/__init__.py
hackwithharsha/main.py
hackwithharsha-0.1.1.dist-info/entry_points.txt
hackwithharsha-0.1.1.dist-info/WHEEL
hackwithharsha-0.1.1.dist-info/METADATA
hackwithharsha-0.1.1.dist-info/RECORD
